README.rst
setup.py
typesys/__init__.py
typesys/type_system.py
typesys.egg-info/PKG-INFO
typesys.egg-info/SOURCES.txt
typesys.egg-info/dependency_links.txt
typesys.egg-info/top_level.txt