Metadata-Version: 1.1
Name: typesys
Version: 0.2.9
Summary: typesys is a python module meant to make it easier to manange types
Home-page: https://github.com/fredgj/typesys
Author: Fredrik Gjertsen
Author-email: f.gjertsen@gmail.com
License: MIT
Keywords: types,type hints,type hinting,type correction,typesystem,typesys
Platform: UNKNOWN
Classifier: Development Status :: 4 - Beta
Classifier: Intended Audience :: Developers
Classifier: License :: OSI Approved :: MIT License
Classifier: Operating System :: OS Independent
Classifier: Programming Language :: Python :: 2
Classifier: Programming Language :: Python :: 3
Classifier: Programming Language :: Python :: Implementation :: CPython
Classifier: Topic :: Utilities
